{
  "indexPage": {
    "title" : "Json works!",
    "introductionText" : ["Предлагаем профессиональный ремонт квартир в Томске.", "В нашей слаженной бригаде 'Дом и Мастер' - только порядочные и квалифицированные отделочники по всем видам ремонтных работ.", "Успех нашей команды держится на профессионализме и стремлении не запятнать репутацию ответсвенных и надёжных мастеров.", "На протяжении многолетних трудов мы ни разу не отступали от своих принципиальных позиций - выполнять все работы по ремонту квартир качественно и в срок!", "Нашими потенциальными клиентами являются как деловые люди, так и заказчики бюджетной категории, желающие получить качественные услуги, при этом не переплачивая посредникам."],
    "introductionList" : ["Работаем сами;", "Без предоплаты;", "Личный опыт - 20 лет;", "Коллектив не курящий;", "Скидки на строительные материалы до 20%;", "Даём гарантию на весь ремонт."],
    "salesOffers" : [
      {
        "title": "Специальное предложение",
        "image": "images/sale1.png",
        "date" : "до 26 июля 2018",
        "copy" : "Закажите поклейку обоев прямо сейчас и получите скидку 35%."
      },
      {
        "title": "Шпатлёвочные смеси в подарок",
        "image": "images/sale2.jpg",
        "date" : "до 1 июля 2018 года",
        "copy" : "При заказе косметического ремонта под ключ Вы получаете профессиональные шпатлёвочные смеси в подарок!"
      }
    ],
    "advertisedPrices" : [
      {"title": "косметический ремонт", "price": 900,  "image": "images/3.png", "copy": "Стоимость - от 900 руб.за м2 по полу. В работу входит замена настенных и напольных покрытий с частичным исправлением дефектов поверхностей, замена плитки в санузлах, шпаклевание потолка с последующей окраской." },
      {"title": "капитальный ремонт", "price": 2500, "image": "images/1.png", "copy": "Цены начинаются от 2500 руб./м. кв. В квартире производится частичная перепланировка, ремонт электрики, разводки водоснабжения и канализации - сантехнические работы, монтаж многоуровневых потолков и элементов декора." },
      {"title": "евроремонт (элитный)", "price": 5000, "image": "images/2.png", "copy": "Цены уже от 5000 руб./м. кв. Отделка проводится следуя утвержденному проекту, с применением эксклюзивных материалов. Весь комплекс ремонтных работ, включая демонтаж перегододок с перепланировкой помещений." }
    ],
    "advertisedServices" : [
      {
        "title": "ШТУКАТУРКА, ШПАКЛЕВКА, ПОКРАСКА",
        "image" : "images/shtukaturnye-maljarnye-raboty.jpg",
        "imageAlt" : "shtukaturnye-maljarnye-raboty"
      },
      {
        "title": "МОНТАЖ КОСТРУКЦИЙ ИЗ ГИПСОКАРТОНА",
        "image" : "images/montazh_gipsokartona.jpg",
        "imageAlt" : "montazh_gipsokartona"
      },
      {
        "title": "ПЛИТОЧНЫЕ РАБОТЫ, РЕМОНТ ВАННОЙ",
        "image" : "images/remont-vannoj.jpg",
        "imageAlt" : "remont-vannoj"
      },
      {
        "title": "ПОКЛЕЙКА ОБОЕВ",
        "image" : "images/poklejka-oboev.jpg",
        "imageAlt" : "poklejka-oboev"
      },
      {
        "title": "УКЛАДКА ЛАМИНАТА",
        "image" : "images/ukladka-laminata.jpg",
        "imageAlt" : "ukladka-laminata"
      },
      {
        "title": "ЭЛЕКТРОМОНТАЖ",
        "image" : "images/jelektro-montazhnye-raboty.jpg",
        "imageAlt" : "jelektro-montazhnye-raboty"
      }
    ]
  },
  "photoPage" : {
    "photoList" : [
      {
        "image" : "images/11.jpg",
        "imageThumbnail" : "images/11.jpg",
        "imageAlt" : "image number 11"
      },
      {
        "image" : "images/12.jpg",
        "imageThumbnail" : "images/12.jpg",
        "imageAlt" : "image number 12"
      },
      {
        "image" : "images/13.jpg",
        "imageThumbnail" : "images/13.jpg",
        "imageAlt" : "image number 13"
      },
      {
        "image" : "images/14.jpg",
        "imageThumbnail" : "images/14.jpg",
        "imageAlt" : "image number 14"
      },
      {
        "image" : "images/15.jpg",
        "imageThumbnail" : "images/15.jpg",
        "imageAlt" : "image number 15"
      },
            {
        "image" : "images/11.jpg",
        "imageThumbnail" : "images/11.jpg",
        "imageAlt" : "image number 11"
      },
      {
        "image" : "images/12.jpg",
        "imageThumbnail" : "images/12.jpg",
        "imageAlt" : "image number 12"
      },
      {
        "image" : "images/13.jpg",
        "imageThumbnail" : "images/13.jpg",
        "imageAlt" : "image number 13"
      },
      {
        "image" : "images/14.jpg",
        "imageThumbnail" : "images/14.jpg",
        "imageAlt" : "image number 14"
      },
      {
        "image" : "images/15.jpg",
        "imageThumbnail" : "images/15.jpg",
        "imageAlt" : "image number 15"
      }
    ]
  },
  "testimonialsPage": {
    "reviewsList" : [
      {
        "name":"",
        "date":"",
        "rating": "",
        "message": ""
      },
      {
        "name":"",
        "date":"",
        "rating": "",
        "message": ""
      },
      {
        "name":"",
        "date":"",
        "rating": "",
        "message": ""
      },
      {
        "name":"",
        "date":"",
        "rating": "",
        "message": ""
      }
    ] 
  }
}